{"title":"18xgirls - Suzie (Spreads Herself Out For Action)","uid":6708447,"size":696132296,"categoryP":"porn","categoryS":"movie_clips","magnet":"?xt=urn:btih:0007d7e50d224bd043b3c5593760352fa2d9a0c9&amp;dn=18xgirls+-+Suzie+%28Spreads+Herself+Out+For+Action%29&amp;tr=udp%3A%2F%2Ftracker.openbittorrent.com%3A80&amp;tr=udp%3A%2F%2Fopen.demonii.com%3A1337&amp;tr=udp%3A%2F%2Ftracker.coppersurfer.tk%3A6969&amp;tr=udp%3A%2F%2Fexodus.desync.com%3A6969","seeders":0,"leechers":0,"uploader":"hhyut","files":1,"time":1317265141,"description":"18xgirls - Suzie (Spreads Herself Out For Action)\n\nScreens:\n\n &lt;a href=&quot;\nhttp://www.Filsfap.com/image.php?imgid=LORFKLU9zSpv&quot; rel=&quot;nofollow&quot; target=&quot;_NEW&quot;&gt;\nhttp://www.Filsfap.com/image.php?imgid=LORFKLU9zSpv&lt;/a&gt;\n\n\n\n","torrent":{"xt":"urn:btih:0007d7e50d224bd043b3c5593760352fa2d9a0c9","amp;dn":"18xgirls+-+Suzie+%28Spreads+Herself+Out+For+Action%29","amp;tr":["udp%3A%2F%2Ftracker.openbittorrent.com%3A80","udp%3A%2F%2Fopen.demonii.com%3A1337","udp%3A%2F%2Ftracker.coppersurfer.tk%3A6969","udp%3A%2F%2Fexodus.desync.com%3A6969"],"infoHash":"0007d7e50d224bd043b3c5593760352fa2d9a0c9","infoHashBuffer":{"type":"Buffer","data":[0,7,215,229,13,34,75,208,67,179,197,89,55,96,53,47,162,217,160,201]},"announce":[],"urlList":[]}}