{"title":"[FirstAnalQuest.com] Vicca","uid":6729081,"size":312365056,"categoryP":"porn","categoryS":"movie_clips","magnet":"?xt=urn:btih:079168b3913dc52a983f82db1dc68913962d6d2e&amp;dn=%5BFirstAnalQuest.com%5D+Vicca&amp;tr=udp%3A%2F%2Ftracker.openbittorrent.com%3A80&amp;tr=udp%3A%2F%2Fopen.demonii.com%3A1337&amp;tr=udp%3A%2F%2Ftracker.coppersurfer.tk%3A6969&amp;tr=udp%3A%2F%2Fexodus.desync.com%3A6969","seeders":0,"leechers":3,"uploader":"chkm8te","files":1,"time":1318060971,"description":"Screens: &lt;a href=&quot;\nhttp://4ufrom.me/viewer.php?file=16o5a634bmsoxnbqvigy.jpg&quot; rel=&quot;nofollow&quot; target=&quot;_NEW&quot;&gt;\nhttp://4ufrom.me/viewer.php?file=16o5a634bmsoxnbqvigy.jpg&lt;/a&gt;","torrent":{"xt":"urn:btih:079168b3913dc52a983f82db1dc68913962d6d2e","amp;dn":"%5BFirstAnalQuest.com%5D+Vicca","amp;tr":["udp%3A%2F%2Ftracker.openbittorrent.com%3A80","udp%3A%2F%2Fopen.demonii.com%3A1337","udp%3A%2F%2Ftracker.coppersurfer.tk%3A6969","udp%3A%2F%2Fexodus.desync.com%3A6969"],"infoHash":"079168b3913dc52a983f82db1dc68913962d6d2e","infoHashBuffer":{"type":"Buffer","data":[7,145,104,179,145,61,197,42,152,63,130,219,29,198,137,19,150,45,109,46]},"announce":[],"urlList":[]}}