{"title":"BBC - The Fades 2011  3 of 6 [MP4-AAC](oan)","uid":6723394,"size":583973834,"categoryP":"video","categoryS":"tv_shows","magnet":"?xt=urn:btih:0dfffd610f4f973d7c707359207f93306d76c21b&amp;dn=BBC+-+The+Fades+2011++3+of+6+%5BMP4-AAC%5D%28oan%29&amp;tr=udp%3A%2F%2Ftracker.openbittorrent.com%3A80&amp;tr=udp%3A%2F%2Fopen.demonii.com%3A1337&amp;tr=udp%3A%2F%2Ftracker.coppersurfer.tk%3A6969&amp;tr=udp%3A%2F%2Fexodus.desync.com%3A6969","seeders":0,"leechers":1,"uploader":"oneanight","files":-1,"time":1317868458,"description":"Fantasy / Horror \n\n\nBBC - The Fades 2011 / 3 of 6 [MP4-AAC](oan)\n\n\n[img]http://anony.ws/di-RQSH.jpg[/img]\n\n\n\nAs Paul's powers manifest themselves, his friendship with Mac and relationship with Jay \nare pushed to breaking point. Meanwhile, a host of new Angelics arrive in town just as the Fades' plans evolve in a chilling new direction.\n\n &lt;a href=&quot;\nhttp://nimga.com/f/Yl34c.jpg&quot; rel=&quot;nofollow&quot; target=&quot;_NEW&quot;&gt;\nhttp://nimga.com/f/Yl34c.jpg&lt;/a&gt;\n\n\n::General::\n\nFormat: MPEG-4\nFile Size: 557 MiB\nOverall Bit Rate: 1 398 Kbps\nDuration: 55mn 40s\nSample: NO\nSubtitles External: NO\n\n::Video Info::\n\nContainer: avc\nVideo Codec Type: x264\nVideo bitrate: 1 200 Kbps\nResolution: 720 X 400 pixels\nAspect ratio(AR): 16.9\nQuality Factor(QF): 0.167\nFrame Rate: 25.000 fps\nSource: (oan).Thanks!!\n\n::Audio Info::\n\nAudio Language: English\nAudio Codec: AAC\nBitrate Mode: Variable\nBitrate: 224 Kbps ((( Stereo )))\nMaximum Bitrate: 576 Kbps\nSample Rate: 48.0 KHz\nChannel Count: 2 channels [Front: L R]","torrent":{"xt":"urn:btih:0dfffd610f4f973d7c707359207f93306d76c21b","amp;dn":"BBC+-+The+Fades+2011++3+of+6+%5BMP4-AAC%5D%28oan%29","amp;tr":["udp%3A%2F%2Ftracker.openbittorrent.com%3A80","udp%3A%2F%2Fopen.demonii.com%3A1337","udp%3A%2F%2Ftracker.coppersurfer.tk%3A6969","udp%3A%2F%2Fexodus.desync.com%3A6969"],"infoHash":"0dfffd610f4f973d7c707359207f93306d76c21b","infoHashBuffer":{"type":"Buffer","data":[13,255,253,97,15,79,151,61,124,112,115,89,32,127,147,48,109,118,194,27]},"announce":[],"urlList":[]}}