{"title":"Barely Legal  24 [DvdRip].mpg","uid":6698678,"size":833579012,"categoryP":"porn","categoryS":"movies","magnet":"?xt=urn:btih:1741a9ff193a9f0383f5f654e7af1305fdfa538c&amp;dn=Barely+Legal++24+%5BDvdRip%5D.mpg&amp;tr=udp%3A%2F%2Ftracker.openbittorrent.com%3A80&amp;tr=udp%3A%2F%2Fopen.demonii.com%3A1337&amp;tr=udp%3A%2F%2Ftracker.coppersurfer.tk%3A6969&amp;tr=udp%3A%2F%2Fexodus.desync.com%3A6969","seeders":0,"leechers":1,"uploader":"SplashPt","files":1,"time":1316877041,"description":"\nBarely Legal  24 [DvdRip].mpg\n\nDescription:\nLook at these smiling faces. Can you blame  the girls for being tickled pink? The newly legal darlings can finally  have all the dick their little pussies desire. Watch as the grateful  cuties grin through mouthfuls of cock. Share in their joy as two of the  teens discover that their tight, tender buttholes are made for banging  too. The babes of BARELY LEGAL #24 are so fucking happy, they could  burst, and so will you.\n\nCast:\nAnna, Jason McCain, Becca Bratt, Precious, Lisa Parks, Craig Moore, Joey Lane, Diamond Legacy, Latin Lover\n\n\nTags: Hardcore, Teen, XxX, Blowjob, Fuck\n\nResolution:   352x240\n\nDuration:     01:21:37\n\t\nSize:\t      794 Mb\n\nScreens:\n &lt;a href=&quot;\nhttp://www.starpix.us/show.php/4636_00.jpg.html&quot; rel=&quot;nofollow&quot; target=&quot;_NEW&quot;&gt;\nhttp://www.starpix.us/show.php/4636_00.jpg.html&lt;/a&gt;\n &lt;a href=&quot;\nhttp://www.starpix.us/show.php/4635_01.jpg.html&quot; rel=&quot;nofollow&quot; target=&quot;_NEW&quot;&gt;\nhttp://www.starpix.us/show.php/4635_01.jpg.html&lt;/a&gt;\n\n\n-----------------------------\n &lt;a href=&quot;\nhttp://hornykitty.com/index.php&quot; rel=&quot;nofollow&quot; target=&quot;_NEW&quot;&gt;\nhttp://hornykitty.com/index.php&lt;/a&gt;\t","torrent":{"xt":"urn:btih:1741a9ff193a9f0383f5f654e7af1305fdfa538c","amp;dn":"Barely+Legal++24+%5BDvdRip%5D.mpg","amp;tr":["udp%3A%2F%2Ftracker.openbittorrent.com%3A80","udp%3A%2F%2Fopen.demonii.com%3A1337","udp%3A%2F%2Ftracker.coppersurfer.tk%3A6969","udp%3A%2F%2Fexodus.desync.com%3A6969"],"infoHash":"1741a9ff193a9f0383f5f654e7af1305fdfa538c","infoHashBuffer":{"type":"Buffer","data":[23,65,169,255,25,58,159,3,131,245,246,84,231,175,19,5,253,250,83,140]},"announce":[],"urlList":[]}}