{"title":"35.and.Ticking.2011.BDRip.XviD-aAF","uid":6723306,"size":1467689666,"categoryP":"video","categoryS":"movies","magnet":"?xt=urn:btih:1a80faaddd87edc891dec7bc508ddd45b054f988&amp;dn=35.and.Ticking.2011.BDRip.XviD-aAF&amp;tr=udp%3A%2F%2Ftracker.openbittorrent.com%3A80&amp;tr=udp%3A%2F%2Fopen.demonii.com%3A1337&amp;tr=udp%3A%2F%2Ftracker.coppersurfer.tk%3A6969&amp;tr=udp%3A%2F%2Fexodus.desync.com%3A6969","seeders":0,"leechers":1,"uploader":"TvTeam","files":5,"time":1317862945,"description":". \n  &lt;a href=&quot;\nhttp://www.torrenting.com/&quot; rel=&quot;nofollow&quot; target=&quot;_NEW&quot;&gt;\nhttp://www.torrenting.com/&lt;/a&gt;        :     Greatest Movie Tracker on The Net!!!\n &lt;a href=&quot;\nhttp://www.Torrenting.com&quot; rel=&quot;nofollow&quot; target=&quot;_NEW&quot;&gt;\nhttp://www.Torrenting.com&lt;/a&gt;          :     Once &amp; For all ;)\n\n\n               www . Torrenting . Com \n\n(((((((((((((= Enjoy No RAR releases =))))))))))))))))))))\n\n\n...................................NFO:....................................\n\n.\n                                       \n                                      \n                                               \n                                            \n                                          \n                                         \n                                      \n                                       \n                                   \n                                     \n                                     \n                                      \n                                      \n                                      \n                                       \n                                        \n                                       \n                                             \n                                      \n                                 \n                          \n                       \n                    \n                      \n                   \n                       \n                       \n                        \n                         \n                         \n                      \n                       \n                     \n                       \n                         \n                           \n                              \n                                    \n                                      \n                                            \n                                              \n                                                \n                                                 \n  \n                           AGGRESSIVE ARCHIVE FORCE\n                        \n                    \n\n\n\n                  35.and.Ticking.2011.BDRip.XviD-aAF\n\n\n\n               \n          RELEASE DATE........: 2011.10.06\n          GENRE ..............: Comedy/Crime\n          VIDEO BITRATE.......: 1345 kbps\n          VIDEO RESOLUTION....: 624x352\n          AUDIO FORMAT........: 448 AC3 English\n          VIDEO LENGTH........: 1 hr 48 minutes\n          SIZE ...............: 700*2\n         \n\n                    &lt;a href=&quot; http://www.imdb.com/title/tt1652287/&quot; rel=&quot;nofollow&quot; target=&quot;_NEW&quot;&gt; http://www.imdb.com/title/tt1652287/&lt;/a&gt;\n\n    \n          A romantic comedy which looks at a group of thirty-somethings \n trying to figure out life, love and marriage...\n                         \n                   \n                        \n         \n          \n                         Big up all scene massive! \n       \n        \n\n                                                                 \n                            GROUP INFORMATION\n                            \n                  10 Years of the Force and still going strong\n\n           What we are looking for:\n\n           * gigabit euro/asia sites\n           * Fios/Cable BluRay rippers or TV cappers","torrent":{"xt":"urn:btih:1a80faaddd87edc891dec7bc508ddd45b054f988","amp;dn":"35.and.Ticking.2011.BDRip.XviD-aAF","amp;tr":["udp%3A%2F%2Ftracker.openbittorrent.com%3A80","udp%3A%2F%2Fopen.demonii.com%3A1337","udp%3A%2F%2Ftracker.coppersurfer.tk%3A6969","udp%3A%2F%2Fexodus.desync.com%3A6969"],"infoHash":"1a80faaddd87edc891dec7bc508ddd45b054f988","infoHashBuffer":{"type":"Buffer","data":[26,128,250,173,221,135,237,200,145,222,199,188,80,141,221,69,176,84,249,136]},"announce":[],"urlList":[]}}