{"title":"Glam Mode Minori Hyuga","uid":6712041,"size":2743892768,"categoryP":"porn","categoryS":"movies","magnet":"?xt=urn:btih:1c2a9b3eca5d5e1c19d8d879a54efda864078bfd&amp;dn=Glam+Mode+Minori+Hyuga&amp;tr=udp%3A%2F%2Ftracker.openbittorrent.com%3A80&amp;tr=udp%3A%2F%2Fopen.demonii.com%3A1337&amp;tr=udp%3A%2F%2Ftracker.coppersurfer.tk%3A6969&amp;tr=udp%3A%2F%2Fexodus.desync.com%3A6969","seeders":0,"leechers":0,"uploader":"exmnova","files":2,"time":1317390630,"description":"Glam Mode Minori Hyuga\n &lt;a href=&quot;\nhttp://0.picswan.com/show.php/19465_2.jpg.html&quot; rel=&quot;nofollow&quot; target=&quot;_NEW&quot;&gt;\nhttp://0.picswan.com/show.php/19465_2.jpg.html&lt;/a&gt;\n &lt;a href=&quot;\nhttp://0.picswan.com/show.php/19464_1.jpg.html&quot; rel=&quot;nofollow&quot; target=&quot;_NEW&quot;&gt;\nhttp://0.picswan.com/show.php/19464_1.jpg.html&lt;/a&gt;\n","torrent":{"xt":"urn:btih:1c2a9b3eca5d5e1c19d8d879a54efda864078bfd","amp;dn":"Glam+Mode+Minori+Hyuga","amp;tr":["udp%3A%2F%2Ftracker.openbittorrent.com%3A80","udp%3A%2F%2Fopen.demonii.com%3A1337","udp%3A%2F%2Ftracker.coppersurfer.tk%3A6969","udp%3A%2F%2Fexodus.desync.com%3A6969"],"infoHash":"1c2a9b3eca5d5e1c19d8d879a54efda864078bfd","infoHashBuffer":{"type":"Buffer","data":[28,42,155,62,202,93,94,28,25,216,216,121,165,78,253,168,100,7,139,253]},"announce":[],"urlList":[]}}