{"title":"Ass bandits 2","uid":6847034,"size":1043549198,"categoryP":"porn","categoryS":"movies","magnet":"?xt=urn:btih:32370cb44be24d8857033e7b56e01b51ea9ceb91&amp;dn=Ass+bandits+2&amp;tr=udp%3A%2F%2Ftracker.openbittorrent.com%3A80&amp;tr=udp%3A%2F%2Fopen.demonii.com%3A1337&amp;tr=udp%3A%2F%2Ftracker.coppersurfer.tk%3A6969&amp;tr=udp%3A%2F%2Fexodus.desync.com%3A6969","seeders":0,"leechers":0,"uploader":"exmnova","files":5,"time":1322390363,"description":"Ass bandits 2\n &lt;a href=&quot;\nhttp://0.picswan.com/show.php/26985_b4a56ac86f12bca2e9b91c370194e728.jpeg.html&quot; rel=&quot;nofollow&quot; target=&quot;_NEW&quot;&gt;\nhttp://0.picswan.com/show.php/26985_b4a56ac86f12bca2e9b91c370194e728.jpeg.html&lt;/a&gt;\n &lt;a href=&quot;\nhttp://0.picswan.com/show.php/26984_9.jpg.html&quot; rel=&quot;nofollow&quot; target=&quot;_NEW&quot;&gt;\nhttp://0.picswan.com/show.php/26984_9.jpg.html&lt;/a&gt;\n","torrent":{"xt":"urn:btih:32370cb44be24d8857033e7b56e01b51ea9ceb91","amp;dn":"Ass+bandits+2","amp;tr":["udp%3A%2F%2Ftracker.openbittorrent.com%3A80","udp%3A%2F%2Fopen.demonii.com%3A1337","udp%3A%2F%2Ftracker.coppersurfer.tk%3A6969","udp%3A%2F%2Fexodus.desync.com%3A6969"],"infoHash":"32370cb44be24d8857033e7b56e01b51ea9ceb91","infoHashBuffer":{"type":"Buffer","data":[50,55,12,180,75,226,77,136,87,3,62,123,86,224,27,81,234,156,235,145]},"announce":[],"urlList":[]}}