{"title":"18 Years Old - Kenna Kane ** HOT **13 OCT 2011","uid":6741897,"size":577524113,"categoryP":"porn","categoryS":"movie_clips","magnet":"?xt=urn:btih:334cea0f38c9358c2b76eb5682de1071d04d2363&amp;dn=18+Years+Old+-+Kenna+Kane+%2A%2A+HOT+%2A%2A13+OCT+2011&amp;tr=udp%3A%2F%2Ftracker.openbittorrent.com%3A80&amp;tr=udp%3A%2F%2Fopen.demonii.com%3A1337&amp;tr=udp%3A%2F%2Ftracker.coppersurfer.tk%3A6969&amp;tr=udp%3A%2F%2Fexodus.desync.com%3A6969","seeders":0,"leechers":1,"uploader":"tvteam369","files":1,"time":1318537966,"description":"SCREENS:\n &lt;a href=&quot;\nhttp://superimg.us/Image.aspx?ImageID=NzA3&quot; rel=&quot;nofollow&quot; target=&quot;_NEW&quot;&gt;\nhttp://superimg.us/Image.aspx?ImageID=NzA3&lt;/a&gt;\n &lt;a href=&quot;\nhttp://superimg.us/Image.aspx?ImageID=NzA4&quot; rel=&quot;nofollow&quot; target=&quot;_NEW&quot;&gt;\nhttp://superimg.us/Image.aspx?ImageID=NzA4&lt;/a&gt;\n\n\nENJOY !!!!!!!!!!!!","torrent":{"xt":"urn:btih:334cea0f38c9358c2b76eb5682de1071d04d2363","amp;dn":"18+Years+Old+-+Kenna+Kane+%2A%2A+HOT+%2A%2A13+OCT+2011","amp;tr":["udp%3A%2F%2Ftracker.openbittorrent.com%3A80","udp%3A%2F%2Fopen.demonii.com%3A1337","udp%3A%2F%2Ftracker.coppersurfer.tk%3A6969","udp%3A%2F%2Fexodus.desync.com%3A6969"],"infoHash":"334cea0f38c9358c2b76eb5682de1071d04d2363","infoHashBuffer":{"type":"Buffer","data":[51,76,234,15,56,201,53,140,43,118,235,86,130,222,16,113,208,77,35,99]},"announce":[],"urlList":[]}}