{"title":"Headspace.2005.Directors.Cut.BDRiP.AC3-5.1.x264-AXED","uid":7412836,"size":1485107085,"categoryP":"video","categoryS":"movies","magnet":"?xt=urn:btih:56f449dd10a80475570f2f16637d23dbb204f1ae&amp;dn=Headspace.2005.Directors.Cut.BDRiP.AC3-5.1.x264-AXED&amp;tr=udp%3A%2F%2Ftracker.openbittorrent.com%3A80&amp;tr=udp%3A%2F%2Fopen.demonii.com%3A1337&amp;tr=udp%3A%2F%2Ftracker.coppersurfer.tk%3A6969&amp;tr=udp%3A%2F%2Fexodus.desync.com%3A6969","seeders":0,"leechers":1,"uploader":"TvTeam","files":5,"time":1341426613,"description":". \n &lt;a href=&quot;\nhttp://www.torrenting.com&quot; rel=&quot;nofollow&quot; target=&quot;_NEW&quot;&gt;\nhttp://www.torrenting.com&lt;/a&gt;          :     Sign up is OPEN for now!!!\n\n\n               www . Torrenting . Com \n\n(((((((((((((= Enjoy No RAR releases =))))))))))))))))))))\n\n\n...................................NFO:....................................\n\n\nEnjoy our Fast Upload.\nFor more info about this release, open .NFO file with notepad ;)","torrent":{"xt":"urn:btih:56f449dd10a80475570f2f16637d23dbb204f1ae","amp;dn":"Headspace.2005.Directors.Cut.BDRiP.AC3-5.1.x264-AXED","amp;tr":["udp%3A%2F%2Ftracker.openbittorrent.com%3A80","udp%3A%2F%2Fopen.demonii.com%3A1337","udp%3A%2F%2Ftracker.coppersurfer.tk%3A6969","udp%3A%2F%2Fexodus.desync.com%3A6969"],"infoHash":"56f449dd10a80475570f2f16637d23dbb204f1ae","infoHashBuffer":{"type":"Buffer","data":[86,244,73,221,16,168,4,117,87,15,47,22,99,125,35,219,178,4,241,174]},"announce":[],"urlList":[]}}