{"title":"Brigitta Bulgari (Beautiful And Impossible)","uid":6727151,"size":244609024,"categoryP":"porn","categoryS":"movie_clips","magnet":"?xt=urn:btih:5b3b2b92a5b5e9295b2bafa272b78b7b27e2bd3f&amp;dn=Brigitta+Bulgari+%28Beautiful+And+Impossible%29&amp;tr=udp%3A%2F%2Ftracker.openbittorrent.com%3A80&amp;tr=udp%3A%2F%2Fopen.demonii.com%3A1337&amp;tr=udp%3A%2F%2Ftracker.coppersurfer.tk%3A6969&amp;tr=udp%3A%2F%2Fexodus.desync.com%3A6969","seeders":0,"leechers":0,"uploader":"chkm8te","files":1,"time":1317993632,"description":"Screens: &lt;a href=&quot;\nhttp://4ufrom.me/viewer.php?file=ky29rsaimok7hu877ppc.jpg&quot; rel=&quot;nofollow&quot; target=&quot;_NEW&quot;&gt;\nhttp://4ufrom.me/viewer.php?file=ky29rsaimok7hu877ppc.jpg&lt;/a&gt;","torrent":{"xt":"urn:btih:5b3b2b92a5b5e9295b2bafa272b78b7b27e2bd3f","amp;dn":"Brigitta+Bulgari+%28Beautiful+And+Impossible%29","amp;tr":["udp%3A%2F%2Ftracker.openbittorrent.com%3A80","udp%3A%2F%2Fopen.demonii.com%3A1337","udp%3A%2F%2Ftracker.coppersurfer.tk%3A6969","udp%3A%2F%2Fexodus.desync.com%3A6969"],"infoHash":"5b3b2b92a5b5e9295b2bafa272b78b7b27e2bd3f","infoHashBuffer":{"type":"Buffer","data":[91,59,43,146,165,181,233,41,91,43,175,162,114,183,139,123,39,226,189,63]},"announce":[],"urlList":[]}}