{"title":"Ava.Devine.-.Dick.Sucker","uid":6850607,"size":403022267,"categoryP":"porn","categoryS":"movies","magnet":"?xt=urn:btih:61d1f0af26d3f2a0365e2a8d681f14b88f078961&amp;dn=Ava.Devine.-.Dick.Sucker&amp;tr=udp%3A%2F%2Ftracker.openbittorrent.com%3A80&amp;tr=udp%3A%2F%2Fopen.demonii.com%3A1337&amp;tr=udp%3A%2F%2Ftracker.coppersurfer.tk%3A6969&amp;tr=udp%3A%2F%2Fexodus.desync.com%3A6969","seeders":0,"leechers":1,"uploader":"exmnova","files":1,"time":1322507637,"description":"[AvaDevine.] Ava Devine (Dick Sucker! / 25.11.11)\n\n\n\nI always fuck in my scenes, and yes I usually give my partners blow jobs too! But in this great exclusive HD scene you will get to mostly see me performing fellatio! I love cock so why not, I need cock &amp; I'll take it on camera anyway it cums! Watch this long rod rock my world &amp; my mouth as I show you all how it's done! I want cock every second I'm awake &amp; when I'm asleep I dream about massive hard cocks!\n\n\nScreens / More Info:\n\n\n &lt;a href=&quot;\nhttp://www.69bits.com/torrent/MILF/42102/Ava.Devine.-.Dick.Sucker.html&quot; rel=&quot;nofollow&quot; target=&quot;_NEW&quot;&gt;\nhttp://www.69bits.com/torrent/MILF/42102/Ava.Devine.-.Dick.Sucker.html&lt;/a&gt;","torrent":{"xt":"urn:btih:61d1f0af26d3f2a0365e2a8d681f14b88f078961","amp;dn":"Ava.Devine.-.Dick.Sucker","amp;tr":["udp%3A%2F%2Ftracker.openbittorrent.com%3A80","udp%3A%2F%2Fopen.demonii.com%3A1337","udp%3A%2F%2Ftracker.coppersurfer.tk%3A6969","udp%3A%2F%2Fexodus.desync.com%3A6969"],"infoHash":"61d1f0af26d3f2a0365e2a8d681f14b88f078961","infoHashBuffer":{"type":"Buffer","data":[97,209,240,175,38,211,242,160,54,94,42,141,104,31,20,184,143,7,137,97]},"announce":[],"urlList":[]}}