{"title":"[PornstarsLikeItBig.com / Brazzers.com] Faye Reagan","uid":6771325,"size":832098823,"categoryP":"porn","categoryS":"movie_clips","magnet":"?xt=urn:btih:683b384f0b078e05b2401eeb0342abdbaae8e5c5&amp;dn=%5BPornstarsLikeItBig.com+%2F+Brazzers.com%5D+Faye+Reagan&amp;tr=udp%3A%2F%2Ftracker.openbittorrent.com%3A80&amp;tr=udp%3A%2F%2Fopen.demonii.com%3A1337&amp;tr=udp%3A%2F%2Ftracker.coppersurfer.tk%3A6969&amp;tr=udp%3A%2F%2Fexodus.desync.com%3A6969","seeders":0,"leechers":4,"uploader":"chkm8te","files":4,"time":1319584776,"description":"Screens: &lt;a href=&quot;\nhttp://4ufrom.me/viewer.php?file=y60kcorr20in42e88czd.jpg&quot; rel=&quot;nofollow&quot; target=&quot;_NEW&quot;&gt;\nhttp://4ufrom.me/viewer.php?file=y60kcorr20in42e88czd.jpg&lt;/a&gt;\n &lt;a href=&quot;\nhttp://4ufrom.me/viewer.php?file=o0yn6qi5kxv5pb6jd7os.jpg&quot; rel=&quot;nofollow&quot; target=&quot;_NEW&quot;&gt;\nhttp://4ufrom.me/viewer.php?file=o0yn6qi5kxv5pb6jd7os.jpg&lt;/a&gt;","torrent":{"xt":"urn:btih:683b384f0b078e05b2401eeb0342abdbaae8e5c5","amp;dn":"%5BPornstarsLikeItBig.com+%2F+Brazzers.com%5D+Faye+Reagan","amp;tr":["udp%3A%2F%2Ftracker.openbittorrent.com%3A80","udp%3A%2F%2Fopen.demonii.com%3A1337","udp%3A%2F%2Ftracker.coppersurfer.tk%3A6969","udp%3A%2F%2Fexodus.desync.com%3A6969"],"infoHash":"683b384f0b078e05b2401eeb0342abdbaae8e5c5","infoHashBuffer":{"type":"Buffer","data":[104,59,56,79,11,7,142,5,178,64,30,235,3,66,171,219,170,232,229,197]},"announce":[],"urlList":[]}}