{"title":"Cowboys And Aliens 2011 Extended BRRIP XVID AbSurdity","uid":6835338,"size":1486315546,"categoryP":"video","categoryS":"movies","magnet":"?xt=urn:btih:6a09fc3b2326c3092b5e4590cda6aaba6bbc8f7d&amp;dn=Cowboys+And+Aliens+2011+Extended+BRRIP+XVID+AbSurdity&amp;tr=udp%3A%2F%2Ftracker.openbittorrent.com%3A80&amp;tr=udp%3A%2F%2Fopen.demonii.com%3A1337&amp;tr=udp%3A%2F%2Ftracker.coppersurfer.tk%3A6969&amp;tr=udp%3A%2F%2Fexodus.desync.com%3A6969","seeders":0,"leechers":0,"uploader":"UltraTorrents","files":4,"time":1322006149,"description":"INFO, POSTER &amp; TRAILER\n                                        &lt;a href=&quot;\nhttp://www.sharepixon.net/movies/cowboys-aliens&quot; rel=&quot;nofollow&quot; target=&quot;_NEW&quot;&gt;\nhttp://www.sharepixon.net/movies/cowboys-aliens&lt;/a&gt;\n\n[url]http://www.sharepixon.net/movies/cowboys-aliens[/url]\n\n\nSCREENSHOTS:\n                                       &lt;a href=&quot;\nhttp://img.sharepixon.net/?v=cowboyipi.png&quot; rel=&quot;nofollow&quot; target=&quot;_NEW&quot;&gt;\nhttp://img.sharepixon.net/?v=cowboyipi.png&lt;/a&gt;  &lt;a href=&quot;\nhttp://img.sharepixon.net/?v=cowboyqeq.png&quot; rel=&quot;nofollow&quot; target=&quot;_NEW&quot;&gt;\nhttp://img.sharepixon.net/?v=cowboyqeq.png&lt;/a&gt;\n\n[url]http://img.sharepixon.net/?v=cowboyipi.png[/url]\t\n[url]http://img.sharepixon.net/?v=cowboyqeq.png[/url]\t\n\t\n\t\t","torrent":{"xt":"urn:btih:6a09fc3b2326c3092b5e4590cda6aaba6bbc8f7d","amp;dn":"Cowboys+And+Aliens+2011+Extended+BRRIP+XVID+AbSurdity","amp;tr":["udp%3A%2F%2Ftracker.openbittorrent.com%3A80","udp%3A%2F%2Fopen.demonii.com%3A1337","udp%3A%2F%2Ftracker.coppersurfer.tk%3A6969","udp%3A%2F%2Fexodus.desync.com%3A6969"],"infoHash":"6a09fc3b2326c3092b5e4590cda6aaba6bbc8f7d","infoHashBuffer":{"type":"Buffer","data":[106,9,252,59,35,38,195,9,43,94,69,144,205,166,170,186,107,188,143,125]},"announce":[],"urlList":[]}}