{"title":"(Sucker Punch Star )Emily Browning Fully Naked Seans in Sleeping","uid":6755337,"size":45456107,"categoryP":"porn","categoryS":"other","magnet":"?xt=urn:btih:6ae354c70c7832ff3ff152ac3c6f5f45e6ccc665&amp;dn=%28Sucker+Punch+Star+%29Emily+Browning+Fully+Naked+Seans+in+Sleeping&amp;tr=udp%3A%2F%2Ftracker.openbittorrent.com%3A80&amp;tr=udp%3A%2F%2Fopen.demonii.com%3A1337&amp;tr=udp%3A%2F%2Ftracker.coppersurfer.tk%3A6969&amp;tr=udp%3A%2F%2Fexodus.desync.com%3A6969","seeders":0,"leechers":3,"uploader":"fuckyou2night","files":-1,"time":1319019685,"description":"                                    SCREENSHOTS\n                  &lt;a href=&quot; http://adultstuff.in/showthread.php?tid=316&quot; rel=&quot;nofollow&quot; target=&quot;_NEW&quot;&gt; http://adultstuff.in/showthread.php?tid=316&lt;/a&gt;","torrent":{"xt":"urn:btih:6ae354c70c7832ff3ff152ac3c6f5f45e6ccc665","amp;dn":"%28Sucker+Punch+Star+%29Emily+Browning+Fully+Naked+Seans+in+Sleeping","amp;tr":["udp%3A%2F%2Ftracker.openbittorrent.com%3A80","udp%3A%2F%2Fopen.demonii.com%3A1337","udp%3A%2F%2Ftracker.coppersurfer.tk%3A6969","udp%3A%2F%2Fexodus.desync.com%3A6969"],"infoHash":"6ae354c70c7832ff3ff152ac3c6f5f45e6ccc665","infoHashBuffer":{"type":"Buffer","data":[106,227,84,199,12,120,50,255,63,241,82,172,60,111,95,69,230,204,198,101]},"announce":[],"urlList":[]}}