{"title":"Norton 360 5.0.0.125 150days fully cracked and trial reset + lat","uid":6696781,"size":276667990,"categoryP":"applications","categoryS":"windows","magnet":"?xt=urn:btih:747903dbac04e74370d4ba0f25d5537be66b0fca&amp;dn=Norton+360+5.0.0.125+150days+fully+cracked+and+trial+reset+%2B+lat&amp;tr=udp%3A%2F%2Ftracker.openbittorrent.com%3A80&amp;tr=udp%3A%2F%2Fopen.demonii.com%3A1337&amp;tr=udp%3A%2F%2Ftracker.coppersurfer.tk%3A6969&amp;tr=udp%3A%2F%2Fexodus.desync.com%3A6969","seeders":0,"leechers":0,"uploader":"salmansk","files":10,"time":1316812286,"description":"\n1st: Install norton 360\n2nd: start norton 360 goto setting and turn of norton temper protection\n3rd: start box ntr and install\n4th: click on 20110922-024-v5i32.exe and than it will promt than click ok....enjoy ur successfully updated also to latest upadte of 9/23/2011\n\nYOULL GET 150DAYS OR 165DAYS\nDEPEND ON YOUR OPERATING SYSTEM\ndone \nenjoyy\n\n\nif ur 150days get over than uninstall norton restart pc than run box ntr and install norton and than follow step 1,2,3,4\n\nYOULL GET once again 150DAYS OR 165DAYS\nDEPEND ON YOUR OPERATING SYSTEM\ndone \nenjoyy","torrent":{"xt":"urn:btih:747903dbac04e74370d4ba0f25d5537be66b0fca","amp;dn":"Norton+360+5.0.0.125+150days+fully+cracked+and+trial+reset+%2B+lat","amp;tr":["udp%3A%2F%2Ftracker.openbittorrent.com%3A80","udp%3A%2F%2Fopen.demonii.com%3A1337","udp%3A%2F%2Ftracker.coppersurfer.tk%3A6969","udp%3A%2F%2Fexodus.desync.com%3A6969"],"infoHash":"747903dbac04e74370d4ba0f25d5537be66b0fca","infoHashBuffer":{"type":"Buffer","data":[116,121,3,219,172,4,231,67,112,212,186,15,37,213,83,123,230,107,15,202]},"announce":[],"urlList":[]}}