{"title":"Flicka.2.2010.NL-subs.xvid.(DutchReleaseTeam)","uid":6703579,"size":606297996,"categoryP":"video","categoryS":"movies","magnet":"?xt=urn:btih:7814f8bc2f5a250577d9bdef22c317954328eb0c&amp;dn=Flicka.2.2010.NL-subs.xvid.%28DutchReleaseTeam%29&amp;tr=udp%3A%2F%2Ftracker.openbittorrent.com%3A80&amp;tr=udp%3A%2F%2Fopen.demonii.com%3A1337&amp;tr=udp%3A%2F%2Ftracker.coppersurfer.tk%3A6969&amp;tr=udp%3A%2F%2Fexodus.desync.com%3A6969","seeders":0,"leechers":0,"uploader":"gorpo3","files":-1,"time":1317072453,"description":"Verenigde Staten\nFamilie\n90 minuten\n\neen zeer mooie film\n\nmet Patrick Warburton, Tammin Sursok en Emily Tennant\n\nCarrie is een tiener uit een grote stad wiens leven op zijn kop gezet wordt wanneer ze verhuist naar een paardenranch in Wyoming, \nom er samen te leven met haar vader. Maar alles verandert wanneer Carrie Flicka ontmoet, een wilde zwarte mustang met een even \nvrije geest en wilskracht als Carrie. De twee vormen een speciale band en Carrie opent haar hart naar haar vader toe en ook naar \neen knappe, lokale jongen. Maar wanneer een jaloerse rivaal Flicka's leven in gevaar brengt, doet Carrie er alles aan om haar \nbeste vriend te redden.\n-\naangeboden door het DutchreleaseTeam:\n\nveel kijk plezier:\n\n&quot;Vrygeven a.u.b!/Seeden please!&quot;\n &lt;a href=&quot;\nhttp://www.moviemeter.nl/film/65969&quot; rel=&quot;nofollow&quot; target=&quot;_NEW&quot;&gt;\nhttp://www.moviemeter.nl/film/65969&lt;/a&gt; \n &lt;a href=&quot;\nhttp://www.imdb.com/title/tt1381767&quot; rel=&quot;nofollow&quot; target=&quot;_NEW&quot;&gt;\nhttp://www.imdb.com/title/tt1381767&lt;/a&gt; ","torrent":{"xt":"urn:btih:7814f8bc2f5a250577d9bdef22c317954328eb0c","amp;dn":"Flicka.2.2010.NL-subs.xvid.%28DutchReleaseTeam%29","amp;tr":["udp%3A%2F%2Ftracker.openbittorrent.com%3A80","udp%3A%2F%2Fopen.demonii.com%3A1337","udp%3A%2F%2Ftracker.coppersurfer.tk%3A6969","udp%3A%2F%2Fexodus.desync.com%3A6969"],"infoHash":"7814f8bc2f5a250577d9bdef22c317954328eb0c","infoHashBuffer":{"type":"Buffer","data":[120,20,248,188,47,90,37,5,119,217,189,239,34,195,23,149,67,40,235,12]},"announce":[],"urlList":[]}}