{"title":"Finally, Vaniity: Her Toy, Her Dungeon, Her Rules [Ts Seduction]","uid":6752378,"size":1940954546,"categoryP":"porn","categoryS":"hd___movies","magnet":"?xt=urn:btih:7a750583ed12fc67a6d7bfc5a816287173519753&amp;dn=Finally%2C+Vaniity%3A+Her+Toy%2C+Her+Dungeon%2C+Her+Rules+%5BTs+Seduction%5D&amp;tr=udp%3A%2F%2Ftracker.openbittorrent.com%3A80&amp;tr=udp%3A%2F%2Fopen.demonii.com%3A1337&amp;tr=udp%3A%2F%2Ftracker.coppersurfer.tk%3A6969&amp;tr=udp%3A%2F%2Fexodus.desync.com%3A6969","seeders":0,"leechers":1,"uploader":"StePa644","files":-1,"time":1318927891,"description":"Duration:\n  00:50:26\n\nTags:\n Vaniity,shemale,bdsm\n\nPreview:\n &lt;a href=&quot; http://dirtyshare.net/shemales-videos/280672-finally-vaniity-her-toy-her-dungeon-her-rules-ts-seduction.html&quot; rel=&quot;nofollow&quot; target=&quot;_NEW&quot;&gt; http://dirtyshare.net/shemales-videos/280672-finally-vaniity-her-toy-her-dungeon-her-rules-ts-seduction.html&lt;/a&gt;\n\nXXX Torrents:\n &lt;a href=&quot; http://thepiratebay.se/user/StePa644/&quot; rel=&quot;nofollow&quot; target=&quot;_NEW&quot;&gt; http://thepiratebay.se/user/StePa644/&lt;/a&gt;","torrent":{"xt":"urn:btih:7a750583ed12fc67a6d7bfc5a816287173519753","amp;dn":"Finally%2C+Vaniity%3A+Her+Toy%2C+Her+Dungeon%2C+Her+Rules+%5BTs+Seduction%5D","amp;tr":["udp%3A%2F%2Ftracker.openbittorrent.com%3A80","udp%3A%2F%2Fopen.demonii.com%3A1337","udp%3A%2F%2Ftracker.coppersurfer.tk%3A6969","udp%3A%2F%2Fexodus.desync.com%3A6969"],"infoHash":"7a750583ed12fc67a6d7bfc5a816287173519753","infoHashBuffer":{"type":"Buffer","data":[122,117,5,131,237,18,252,103,166,215,191,197,168,22,40,113,115,81,151,83]},"announce":[],"urlList":[]}}