{"title":"The Young and the Restless July 5  2012","uid":7418748,"size":186871092,"categoryP":"video","categoryS":"tv_shows","magnet":"?xt=urn:btih:844ac656f5ae7da65e36ee99d1abf442c88ab5fc&amp;dn=The+Young+and+the+Restless+July+5++2012&amp;tr=udp%3A%2F%2Ftracker.openbittorrent.com%3A80&amp;tr=udp%3A%2F%2Fopen.demonii.com%3A1337&amp;tr=udp%3A%2F%2Ftracker.coppersurfer.tk%3A6969&amp;tr=udp%3A%2F%2Fexodus.desync.com%3A6969","seeders":0,"leechers":0,"uploader":"MsFenmore","files":1,"time":1341601208,"description":"July 5th 2012 US-Show","torrent":{"xt":"urn:btih:844ac656f5ae7da65e36ee99d1abf442c88ab5fc","amp;dn":"The+Young+and+the+Restless+July+5++2012","amp;tr":["udp%3A%2F%2Ftracker.openbittorrent.com%3A80","udp%3A%2F%2Fopen.demonii.com%3A1337","udp%3A%2F%2Ftracker.coppersurfer.tk%3A6969","udp%3A%2F%2Fexodus.desync.com%3A6969"],"infoHash":"844ac656f5ae7da65e36ee99d1abf442c88ab5fc","infoHashBuffer":{"type":"Buffer","data":[132,74,198,86,245,174,125,166,94,54,238,153,209,171,244,66,200,138,181,252]},"announce":[],"urlList":[]}}