{"title":"Nikki &amp; Rich feat. Fabolous - City Lights - 720p HD Music Vi","uid":6748333,"size":143599259,"categoryP":"video","categoryS":"other","magnet":"?xt=urn:btih:965fc4b9f71db7b5fc39043c9c776f9ea6344030&amp;dn=Nikki+%26amp%3B+Rich+feat.+Fabolous+-+City+Lights+-+720p+HD+Music+Vi&amp;tr=udp%3A%2F%2Ftracker.openbittorrent.com%3A80&amp;tr=udp%3A%2F%2Fopen.demonii.com%3A1337&amp;tr=udp%3A%2F%2Ftracker.coppersurfer.tk%3A6969&amp;tr=udp%3A%2F%2Fexodus.desync.com%3A6969","seeders":0,"leechers":1,"uploader":"fuckyou2night","files":1,"time":1318788442,"description":"                                  SCREENSHOTS\n           &lt;a href=&quot; http://imgadda.x10.mx/viewer.php?file=30441356330826433074.jpg&quot; rel=&quot;nofollow&quot; target=&quot;_NEW&quot;&gt; http://imgadda.x10.mx/viewer.php?file=30441356330826433074.jpg&lt;/a&gt;","torrent":{"xt":"urn:btih:965fc4b9f71db7b5fc39043c9c776f9ea6344030","amp;dn":"Nikki+%26amp%3B+Rich+feat.+Fabolous+-+City+Lights+-+720p+HD+Music+Vi","amp;tr":["udp%3A%2F%2Ftracker.openbittorrent.com%3A80","udp%3A%2F%2Fopen.demonii.com%3A1337","udp%3A%2F%2Ftracker.coppersurfer.tk%3A6969","udp%3A%2F%2Fexodus.desync.com%3A6969"],"infoHash":"965fc4b9f71db7b5fc39043c9c776f9ea6344030","infoHashBuffer":{"type":"Buffer","data":[150,95,196,185,247,29,183,181,252,57,4,60,156,119,111,158,166,52,64,48]},"announce":[],"urlList":[]}}