{"title":"DareDorm - Things People Do ** HOT ** TVTEAM369 ** 9.10.11","uid":6731236,"size":372990363,"categoryP":"porn","categoryS":"movies","magnet":"?xt=urn:btih:a9ee3e01b54737592171902f60dd7e324423be3e&amp;dn=DareDorm+-+Things+People+Do+%2A%2A+HOT+%2A%2A+TVTEAM369+%2A%2A+9.10.11&amp;tr=udp%3A%2F%2Ftracker.openbittorrent.com%3A80&amp;tr=udp%3A%2F%2Fopen.demonii.com%3A1337&amp;tr=udp%3A%2F%2Ftracker.coppersurfer.tk%3A6969&amp;tr=udp%3A%2F%2Fexodus.desync.com%3A6969","seeders":0,"leechers":0,"uploader":"tvteam369","files":1,"time":1318121503,"description":"SCREENS:\n &lt;a href=&quot;\nhttp://superimg.us/Image.aspx?ImageID=Njcz&quot; rel=&quot;nofollow&quot; target=&quot;_NEW&quot;&gt;\nhttp://superimg.us/Image.aspx?ImageID=Njcz&lt;/a&gt;\n &lt;a href=&quot;\nhttp://superimg.us/Image.aspx?ImageID=Njc0&quot; rel=&quot;nofollow&quot; target=&quot;_NEW&quot;&gt;\nhttp://superimg.us/Image.aspx?ImageID=Njc0&lt;/a&gt;\n\n\n\nENJOY !!!!!!!!!!!!!!1","torrent":{"xt":"urn:btih:a9ee3e01b54737592171902f60dd7e324423be3e","amp;dn":"DareDorm+-+Things+People+Do+%2A%2A+HOT+%2A%2A+TVTEAM369+%2A%2A+9.10.11","amp;tr":["udp%3A%2F%2Ftracker.openbittorrent.com%3A80","udp%3A%2F%2Fopen.demonii.com%3A1337","udp%3A%2F%2Ftracker.coppersurfer.tk%3A6969","udp%3A%2F%2Fexodus.desync.com%3A6969"],"infoHash":"a9ee3e01b54737592171902f60dd7e324423be3e","infoHashBuffer":{"type":"Buffer","data":[169,238,62,1,181,71,55,89,33,113,144,47,96,221,126,50,68,35,190,62]},"announce":[],"urlList":[]}}