{"title":"Ciudad de los hombres.avi","uid":7424734,"size":705345536,"categoryP":"video","categoryS":"movies","magnet":"?xt=urn:btih:b2b19bf8be71c7cbf50a0a99bd3b4dcbac78211d&amp;dn=Ciudad+de+los+hombres.avi&amp;tr=udp%3A%2F%2Ftracker.openbittorrent.com%3A80&amp;tr=udp%3A%2F%2Fopen.demonii.com%3A1337&amp;tr=udp%3A%2F%2Ftracker.coppersurfer.tk%3A6969&amp;tr=udp%3A%2F%2Fexodus.desync.com%3A6969","seeders":0,"leechers":3,"uploader":"guerrera6","files":1,"time":1341771238,"description":"MPEG4","torrent":{"xt":"urn:btih:b2b19bf8be71c7cbf50a0a99bd3b4dcbac78211d","amp;dn":"Ciudad+de+los+hombres.avi","amp;tr":["udp%3A%2F%2Ftracker.openbittorrent.com%3A80","udp%3A%2F%2Fopen.demonii.com%3A1337","udp%3A%2F%2Ftracker.coppersurfer.tk%3A6969","udp%3A%2F%2Fexodus.desync.com%3A6969"],"infoHash":"b2b19bf8be71c7cbf50a0a99bd3b4dcbac78211d","infoHashBuffer":{"type":"Buffer","data":[178,177,155,248,190,113,199,203,245,10,10,153,189,59,77,203,172,120,33,29]},"announce":[],"urlList":[]}}