{"title":"Vanessa Cage, Nicole Aniston &amp; Sara Monroe - Supermarket Dic","uid":6781307,"size":539030455,"categoryP":"porn","categoryS":"movie_clips","magnet":"?xt=urn:btih:b51b7304f7834a21c29949b2ae8cd000f13ad781&amp;dn=Vanessa+Cage%2C+Nicole+Aniston+%26amp%3B+Sara+Monroe+-+Supermarket+Dic&amp;tr=udp%3A%2F%2Ftracker.openbittorrent.com%3A80&amp;tr=udp%3A%2F%2Fopen.demonii.com%3A1337&amp;tr=udp%3A%2F%2Ftracker.coppersurfer.tk%3A6969&amp;tr=udp%3A%2F%2Fexodus.desync.com%3A6969","seeders":0,"leechers":1,"uploader":"jabber1","files":1,"time":1319913251,"description":"Vanessa Cage, Nicole Aniston &amp; Sara Monroe - Supermarket Dick (Fuckteamfive/BangBros) **10.28.2011**\n\nScreens: &lt;a href=&quot;\nhttp://imagerotica.com/?v=FSbJ9.jpg&quot; rel=&quot;nofollow&quot; target=&quot;_NEW&quot;&gt;\nhttp://imagerotica.com/?v=FSbJ9.jpg&lt;/a&gt; &lt;a href=&quot;\nhttp://imagerotica.com/?v=U6vld.jpg&quot; rel=&quot;nofollow&quot; target=&quot;_NEW&quot;&gt;\nhttp://imagerotica.com/?v=U6vld.jpg&lt;/a&gt; &lt;a href=&quot;\nhttp://imagerotica.com/?v=eVLUK.jpg&quot; rel=&quot;nofollow&quot; target=&quot;_NEW&quot;&gt;\nhttp://imagerotica.com/?v=eVLUK.jpg&lt;/a&gt; &lt;a href=&quot;\nhttp://imagerotica.com/?v=Vgxoh.jpg&quot; rel=&quot;nofollow&quot; target=&quot;_NEW&quot;&gt;\nhttp://imagerotica.com/?v=Vgxoh.jpg&lt;/a&gt; &lt;a href=&quot;\nhttp://imagerotica.com/?v=9DchT.jpg&quot; rel=&quot;nofollow&quot; target=&quot;_NEW&quot;&gt;\nhttp://imagerotica.com/?v=9DchT.jpg&lt;/a&gt; &lt;a href=&quot;\nhttp://imagerotica.com/?v=yEjGp.jpg&quot; rel=&quot;nofollow&quot; target=&quot;_NEW&quot;&gt;\nhttp://imagerotica.com/?v=yEjGp.jpg&lt;/a&gt;\n\nCasts:\nVanessa Cage, Nicole Aniston &amp; Sara Monroe\n\nDesc:\nSo me and the girls were shopping at the Grocery store. We were looking for some Ginger snaps. When one of the girl ran into a guy by the cookie isle. Sure enough these girls work their magic and get him to invite them over to his house. Before we left we picked up one more chump, his friend. These guys dont know what they got themselves into because these are the Baddest, Horniest pornstars on the block! And they were ready to fuck, Fuck Team Five style. ","torrent":{"xt":"urn:btih:b51b7304f7834a21c29949b2ae8cd000f13ad781","amp;dn":"Vanessa+Cage%2C+Nicole+Aniston+%26amp%3B+Sara+Monroe+-+Supermarket+Dic","amp;tr":["udp%3A%2F%2Ftracker.openbittorrent.com%3A80","udp%3A%2F%2Fopen.demonii.com%3A1337","udp%3A%2F%2Ftracker.coppersurfer.tk%3A6969","udp%3A%2F%2Fexodus.desync.com%3A6969"],"infoHash":"b51b7304f7834a21c29949b2ae8cd000f13ad781","infoHashBuffer":{"type":"Buffer","data":[181,27,115,4,247,131,74,33,194,153,73,178,174,140,208,0,241,58,215,129]},"announce":[],"urlList":[]}}