{"title":"Insex-------Clip_No_34__Test_822_1_Insex.rm","uid":6766406,"size":88252108,"categoryP":"porn","categoryS":"movie_clips","magnet":"?xt=urn:btih:bdfe34c89629f3f8e5911fa9ad2ced50e857c0cf&amp;dn=Insex-------Clip_No_34__Test_822_1_Insex.rm&amp;tr=udp%3A%2F%2Ftracker.openbittorrent.com%3A80&amp;tr=udp%3A%2F%2Fopen.demonii.com%3A1337&amp;tr=udp%3A%2F%2Ftracker.coppersurfer.tk%3A6969&amp;tr=udp%3A%2F%2Fexodus.desync.com%3A6969","seeders":0,"leechers":1,"uploader":"merzedes","files":1,"time":1319401200,"description":"Insex\\Clip_No_34__Test_822_1_Insex.rm\n\n\n\nScreens &lt;a href=&quot; http://bayimg.com/nAkPEaADJ&quot; rel=&quot;nofollow&quot; target=&quot;_NEW&quot;&gt; http://bayimg.com/nAkPEaADJ&lt;/a&gt;\n\n\n\nCheerz  :-)","torrent":{"xt":"urn:btih:bdfe34c89629f3f8e5911fa9ad2ced50e857c0cf","amp;dn":"Insex-------Clip_No_34__Test_822_1_Insex.rm","amp;tr":["udp%3A%2F%2Ftracker.openbittorrent.com%3A80","udp%3A%2F%2Fopen.demonii.com%3A1337","udp%3A%2F%2Ftracker.coppersurfer.tk%3A6969","udp%3A%2F%2Fexodus.desync.com%3A6969"],"infoHash":"bdfe34c89629f3f8e5911fa9ad2ced50e857c0cf","infoHashBuffer":{"type":"Buffer","data":[189,254,52,200,150,41,243,248,229,145,31,169,173,44,237,80,232,87,192,207]},"announce":[],"urlList":[]}}