{"title":"hotsexyplumpers.com - Bomboncito - Cubana Chubby - 444 pics","uid":6745149,"size":64041151,"categoryP":"porn","categoryS":"pictures","magnet":"?xt=urn:btih:c0eb92d89cc79a45aa7f62feb22cdc002db45ea5&amp;dn=hotsexyplumpers.com+-+Bomboncito+-+Cubana+Chubby+-+444+pics&amp;tr=udp%3A%2F%2Ftracker.openbittorrent.com%3A80&amp;tr=udp%3A%2F%2Fopen.demonii.com%3A1337&amp;tr=udp%3A%2F%2Ftracker.coppersurfer.tk%3A6969&amp;tr=udp%3A%2F%2Fexodus.desync.com%3A6969","seeders":0,"leechers":7,"uploader":"bestec1234","files":-1,"time":1318658861,"description":"Full size previews:\n &lt;a href=&quot;\nhttp://www.imagebam.com/gallery/15xttm4yrm7wso5huewi1hxv63yunhle/&quot; rel=&quot;nofollow&quot; target=&quot;_NEW&quot;&gt;\nhttp://www.imagebam.com/gallery/15xttm4yrm7wso5huewi1hxv63yunhle/&lt;/a&gt;","torrent":{"xt":"urn:btih:c0eb92d89cc79a45aa7f62feb22cdc002db45ea5","amp;dn":"hotsexyplumpers.com+-+Bomboncito+-+Cubana+Chubby+-+444+pics","amp;tr":["udp%3A%2F%2Ftracker.openbittorrent.com%3A80","udp%3A%2F%2Fopen.demonii.com%3A1337","udp%3A%2F%2Ftracker.coppersurfer.tk%3A6969","udp%3A%2F%2Fexodus.desync.com%3A6969"],"infoHash":"c0eb92d89cc79a45aa7f62feb22cdc002db45ea5","infoHashBuffer":{"type":"Buffer","data":[192,235,146,216,156,199,154,69,170,127,98,254,178,44,220,0,45,180,94,165]},"announce":[],"urlList":[]}}