{"title":"Deadheads 2011 480p BRRip x264","uid":6831792,"size":1019293140,"categoryP":"video","categoryS":"movies","magnet":"?xt=urn:btih:c0f21c0a44e363d6ed2d637cafcab90871f87fc6&amp;dn=Deadheads+2011+480p+BRRip+x264&amp;tr=udp%3A%2F%2Ftracker.openbittorrent.com%3A80&amp;tr=udp%3A%2F%2Fopen.demonii.com%3A1337&amp;tr=udp%3A%2F%2Ftracker.coppersurfer.tk%3A6969&amp;tr=udp%3A%2F%2Fexodus.desync.com%3A6969","seeders":0,"leechers":0,"uploader":"SF039","files":-1,"time":1321894441,"description":"+----------+-----------------------------+\n| Title    |                   Deadheads |\n+----------+-----------------------------+\n| Year     |                        2011 |\n+----------+-----------------------------+\n| Duration |                      1h34mn |\n+----------+-----------------------------+\n| Format   |                         MP4 |\n+----------+-----------------------------+\n| Video    | x264 @ 1298Kbps @ 23.976fps |\n+----------+-----------------------------+\n| Audio    |     aac @ 128Kbps @ 44.1KHz |\n+----------+-----------------------------+\n| Size     |                   848x480px |\n+----------+-----------------------------+\n\nEnjoy! ;)\n","torrent":{"xt":"urn:btih:c0f21c0a44e363d6ed2d637cafcab90871f87fc6","amp;dn":"Deadheads+2011+480p+BRRip+x264","amp;tr":["udp%3A%2F%2Ftracker.openbittorrent.com%3A80","udp%3A%2F%2Fopen.demonii.com%3A1337","udp%3A%2F%2Ftracker.coppersurfer.tk%3A6969","udp%3A%2F%2Fexodus.desync.com%3A6969"],"infoHash":"c0f21c0a44e363d6ed2d637cafcab90871f87fc6","infoHashBuffer":{"type":"Buffer","data":[192,242,28,10,68,227,99,214,237,45,99,124,175,202,185,8,113,248,127,198]},"announce":[],"urlList":[]}}