{"title":"atkhairy.com.Lucke.058.4-clips.XXX.[GoldenPirates]","uid":6848814,"size":630589894,"categoryP":"porn","categoryS":"movie_clips","magnet":"?xt=urn:btih:c692e3eeb2a8b49ff95a6cea2a694e402cf63204&amp;dn=atkhairy.com.Lucke.058.4-clips.XXX.%5BGoldenPirates%5D&amp;tr=udp%3A%2F%2Ftracker.openbittorrent.com%3A80&amp;tr=udp%3A%2F%2Fopen.demonii.com%3A1337&amp;tr=udp%3A%2F%2Ftracker.coppersurfer.tk%3A6969&amp;tr=udp%3A%2F%2Fexodus.desync.com%3A6969","seeders":0,"leechers":0,"uploader":"GoldenPirates","files":-1,"time":1322444250,"description":"Another torrent from goldenpirates.org\n\nno viruses, no shit, no Bullshit, just pure PORN!\n\nSite:     &lt;a href=&quot;\nhttp://www.atkhairy.com&quot; rel=&quot;nofollow&quot; target=&quot;_NEW&quot;&gt;\nhttp://www.atkhairy.com&lt;/a&gt;\n\nTeam:               &lt;a href=&quot;\nhttp://goldenpirates.org&quot; rel=&quot;nofollow&quot; target=&quot;_NEW&quot;&gt;\nhttp://goldenpirates.org&lt;/a&gt;\n\nUploader/Ripper: goldenPirates\n\n\nMore Golden releases here:               &lt;a href=&quot;\nhttp://thepiratebay.se/user/Goldenpirates&quot; rel=&quot;nofollow&quot; target=&quot;_NEW&quot;&gt;\nhttp://thepiratebay.se/user/Goldenpirates&lt;/a&gt;\nand here:               &lt;a href=&quot;\nhttp://blog.goldenpirates.org/&quot; rel=&quot;nofollow&quot; target=&quot;_NEW&quot;&gt;\nhttp://blog.goldenpirates.org/&lt;/a&gt;\n\nEnjoy! \n\nScreenshots: &lt;a href=&quot;\nhttp://media.goldenpirates.org/go.php?eilk1b7lbd0fvaridyjytky1hp4c&quot; rel=&quot;nofollow&quot; target=&quot;_NEW&quot;&gt;\nhttp://media.goldenpirates.org/go.php?eilk1b7lbd0fvaridyjytky1hp4c&lt;/a&gt; &lt;a href=&quot;\nhttp://media.goldenpirates.org/go.php?is3fsf8k7zx7xsqxweyeerbili0&quot; rel=&quot;nofollow&quot; target=&quot;_NEW&quot;&gt;\nhttp://media.goldenpirates.org/go.php?is3fsf8k7zx7xsqxweyeerbili0&lt;/a&gt; &lt;a href=&quot;\nhttp://media.goldenpirates.org/go.php?r8e0zhorwva3v916rr2n51jqc1&quot; rel=&quot;nofollow&quot; target=&quot;_NEW&quot;&gt;\nhttp://media.goldenpirates.org/go.php?r8e0zhorwva3v916rr2n51jqc1&lt;/a&gt; &lt;a href=&quot;\nhttp://media.goldenpirates.org/go.php?m9ac4aq89ifrw02bdcq0uxqe555w&quot; rel=&quot;nofollow&quot; target=&quot;_NEW&quot;&gt;\nhttp://media.goldenpirates.org/go.php?m9ac4aq89ifrw02bdcq0uxqe555w&lt;/a&gt;\n\nStoryboards: &lt;a href=&quot;\nhttp://media.goldenpirates.org/go.php?zsqk11x5amcj5rabbdn2ngycv3&quot; rel=&quot;nofollow&quot; target=&quot;_NEW&quot;&gt;\nhttp://media.goldenpirates.org/go.php?zsqk11x5amcj5rabbdn2ngycv3&lt;/a&gt; &lt;a href=&quot;\nhttp://media.goldenpirates.org/go.php?l3j3l5kc5eo8jcc266zuacvjkmh&quot; rel=&quot;nofollow&quot; target=&quot;_NEW&quot;&gt;\nhttp://media.goldenpirates.org/go.php?l3j3l5kc5eo8jcc266zuacvjkmh&lt;/a&gt; &lt;a href=&quot;\nhttp://media.goldenpirates.org/go.php?xoyirgkbl4oqibx1n02te1mpch9x&quot; rel=&quot;nofollow&quot; target=&quot;_NEW&quot;&gt;\nhttp://media.goldenpirates.org/go.php?xoyirgkbl4oqibx1n02te1mpch9x&lt;/a&gt; &lt;a href=&quot;\nhttp://media.goldenpirates.org/go.php?70c8z16yfs537yhuxazt6svru9n&quot; rel=&quot;nofollow&quot; target=&quot;_NEW&quot;&gt;\nhttp://media.goldenpirates.org/go.php?70c8z16yfs537yhuxazt6svru9n&lt;/a&gt;\n\n--\n\nlaLMlAadb","torrent":{"xt":"urn:btih:c692e3eeb2a8b49ff95a6cea2a694e402cf63204","amp;dn":"atkhairy.com.Lucke.058.4-clips.XXX.%5BGoldenPirates%5D","amp;tr":["udp%3A%2F%2Ftracker.openbittorrent.com%3A80","udp%3A%2F%2Fopen.demonii.com%3A1337","udp%3A%2F%2Ftracker.coppersurfer.tk%3A6969","udp%3A%2F%2Fexodus.desync.com%3A6969"],"infoHash":"c692e3eeb2a8b49ff95a6cea2a694e402cf63204","infoHashBuffer":{"type":"Buffer","data":[198,146,227,238,178,168,180,159,249,90,108,234,42,105,78,64,44,246,50,4]},"announce":[],"urlList":[]}}