{"title":"Ass.Bangers.XXX.DVDRip.XviD","uid":6754175,"size":2298288128,"categoryP":"porn","categoryS":"movies","magnet":"?xt=urn:btih:c78731365f4f9acf383dc9047f62c53846f189fe&amp;dn=Ass.Bangers.XXX.DVDRip.XviD&amp;tr=udp%3A%2F%2Ftracker.openbittorrent.com%3A80&amp;tr=udp%3A%2F%2Fopen.demonii.com%3A1337&amp;tr=udp%3A%2F%2Ftracker.coppersurfer.tk%3A6969&amp;tr=udp%3A%2F%2Fexodus.desync.com%3A6969","seeders":0,"leechers":1,"uploader":"exmnova","files":6,"time":1318979765,"description":"Ass.Bangers.XXX.DVDRip.XviD\n\n\n\nStarring:   Christina Bella, Aleska Diamond, Aspen, Jessika Lux, Andy Brown, David Perry\n\n\n\nScreens / More Info:\n\n\n &lt;a href=&quot;\nhttp://www.69bits.com/torrent/Gonzo/39396/Ass.Bangers.XXX.DVDRip.XviD.html&quot; rel=&quot;nofollow&quot; target=&quot;_NEW&quot;&gt;\nhttp://www.69bits.com/torrent/Gonzo/39396/Ass.Bangers.XXX.DVDRip.XviD.html&lt;/a&gt;","torrent":{"xt":"urn:btih:c78731365f4f9acf383dc9047f62c53846f189fe","amp;dn":"Ass.Bangers.XXX.DVDRip.XviD","amp;tr":["udp%3A%2F%2Ftracker.openbittorrent.com%3A80","udp%3A%2F%2Fopen.demonii.com%3A1337","udp%3A%2F%2Ftracker.coppersurfer.tk%3A6969","udp%3A%2F%2Fexodus.desync.com%3A6969"],"infoHash":"c78731365f4f9acf383dc9047f62c53846f189fe","infoHashBuffer":{"type":"Buffer","data":[199,135,49,54,95,79,154,207,56,61,201,4,127,98,197,56,70,241,137,254]},"announce":[],"urlList":[]}}