{"title":"Big.Tit.Fanatic.XXX.DVDRip.XviD-Jiggly","uid":6764750,"size":2196276277,"categoryP":"porn","categoryS":"movies","magnet":"?xt=urn:btih:c8bb81092d6fc12707967239bb4f284405fc61d0&amp;dn=Big.Tit.Fanatic.XXX.DVDRip.XviD-Jiggly&amp;tr=udp%3A%2F%2Ftracker.openbittorrent.com%3A80&amp;tr=udp%3A%2F%2Fopen.demonii.com%3A1337&amp;tr=udp%3A%2F%2Ftracker.coppersurfer.tk%3A6969&amp;tr=udp%3A%2F%2Fexodus.desync.com%3A6969","seeders":0,"leechers":2,"uploader":"Rabiner","files":5,"time":1319328466,"description":"Big Tit Fanatic XXX DVDRip XviD-Jiggly\n\n\n &lt;a href=&quot;\nhttp://www.imagesnake.com/img/15891/1.jpg&quot; rel=&quot;nofollow&quot; target=&quot;_NEW&quot;&gt;\nhttp://www.imagesnake.com/img/15891/1.jpg&lt;/a&gt;\n &lt;a href=&quot;\nhttp://www.imagesnake.com/img/15892/2.jpg&quot; rel=&quot;nofollow&quot; target=&quot;_NEW&quot;&gt;\nhttp://www.imagesnake.com/img/15892/2.jpg&lt;/a&gt;\n &lt;a href=&quot;\nhttp://www.imagesnake.com/img/15893/3.jpg&quot; rel=&quot;nofollow&quot; target=&quot;_NEW&quot;&gt;\nhttp://www.imagesnake.com/img/15893/3.jpg&lt;/a&gt;\n &lt;a href=&quot;\nhttp://www.imagesnake.com/img/15894/front.jpg&quot; rel=&quot;nofollow&quot; target=&quot;_NEW&quot;&gt;\nhttp://www.imagesnake.com/img/15894/front.jpg&lt;/a&gt;","torrent":{"xt":"urn:btih:c8bb81092d6fc12707967239bb4f284405fc61d0","amp;dn":"Big.Tit.Fanatic.XXX.DVDRip.XviD-Jiggly","amp;tr":["udp%3A%2F%2Ftracker.openbittorrent.com%3A80","udp%3A%2F%2Fopen.demonii.com%3A1337","udp%3A%2F%2Ftracker.coppersurfer.tk%3A6969","udp%3A%2F%2Fexodus.desync.com%3A6969"],"infoHash":"c8bb81092d6fc12707967239bb4f284405fc61d0","infoHashBuffer":{"type":"Buffer","data":[200,187,129,9,45,111,193,39,7,150,114,57,187,79,40,68,5,252,97,208]},"announce":[],"urlList":[]}}