{"title":"The Tired Captain: A Dracula Encounter - Rafe McGregor","uid":6713049,"size":19853169,"categoryP":"audio","categoryS":"audio_books","magnet":"?xt=urn:btih:d0a5e331f848828ebd6b92dd2712eeda2238d2f7&amp;dn=The+Tired+Captain%3A+A+Dracula+Encounter+-+Rafe+McGregor&amp;tr=udp%3A%2F%2Ftracker.openbittorrent.com%3A80&amp;tr=udp%3A%2F%2Fopen.demonii.com%3A1337&amp;tr=udp%3A%2F%2Ftracker.coppersurfer.tk%3A6969&amp;tr=udp%3A%2F%2Fexodus.desync.com%3A6969","seeders":0,"leechers":0,"uploader":"neil1966hardy","files":3,"time":1317432383,"description":"The Tired Captain: A Dracula Encounter\nUNABRIDGED\nby Rafe McGregor\nNarrated by David Ian Davies\nLength: 40 minutes\n\nPublisher's Summary\n\nEngland, 1893. Chief Inspector Roderick Langham of Scotland Yard is asked to investigate the discovery of a Russian cargo schooner whose crew has vanished except for its captain, who is found dead, tied to the ship's wheel. The captain's log speaks of strange cargo aboard and the crew members disappearing one after another.\n\n\nEnjoy and Seed!!","torrent":{"xt":"urn:btih:d0a5e331f848828ebd6b92dd2712eeda2238d2f7","amp;dn":"The+Tired+Captain%3A+A+Dracula+Encounter+-+Rafe+McGregor","amp;tr":["udp%3A%2F%2Ftracker.openbittorrent.com%3A80","udp%3A%2F%2Fopen.demonii.com%3A1337","udp%3A%2F%2Ftracker.coppersurfer.tk%3A6969","udp%3A%2F%2Fexodus.desync.com%3A6969"],"infoHash":"d0a5e331f848828ebd6b92dd2712eeda2238d2f7","infoHashBuffer":{"type":"Buffer","data":[208,165,227,49,248,72,130,142,189,107,146,221,39,18,238,218,34,56,210,247]},"announce":[],"urlList":[]}}