{"title":"A-Ha - Original Album Series (5CD Boxset) (2011)","uid":6725536,"size":518489766,"categoryP":"audio","categoryS":"music","magnet":"?xt=urn:btih:d377d0e6e57eeade17f86da2efb6416970f88b85&amp;dn=A-Ha+-+Original+Album+Series+%285CD+Boxset%29+%282011%29&amp;tr=udp%3A%2F%2Ftracker.openbittorrent.com%3A80&amp;tr=udp%3A%2F%2Fopen.demonii.com%3A1337&amp;tr=udp%3A%2F%2Ftracker.coppersurfer.tk%3A6969&amp;tr=udp%3A%2F%2Fexodus.desync.com%3A6969","seeders":0,"leechers":0,"uploader":"torggatan","files":58,"time":1317930070,"description":"a-ha- orginginal album series 5 cd boxsest releses today enyoy 2011 full albums","torrent":{"xt":"urn:btih:d377d0e6e57eeade17f86da2efb6416970f88b85","amp;dn":"A-Ha+-+Original+Album+Series+%285CD+Boxset%29+%282011%29","amp;tr":["udp%3A%2F%2Ftracker.openbittorrent.com%3A80","udp%3A%2F%2Fopen.demonii.com%3A1337","udp%3A%2F%2Ftracker.coppersurfer.tk%3A6969","udp%3A%2F%2Fexodus.desync.com%3A6969"],"infoHash":"d377d0e6e57eeade17f86da2efb6416970f88b85","infoHashBuffer":{"type":"Buffer","data":[211,119,208,230,229,126,234,222,23,248,109,162,239,182,65,105,112,248,139,133]},"announce":[],"urlList":[]}}