{"title":"Hop (2011) - Blu ray - 720p - Dual Audio (Hindi-English) - Team ","uid":6707502,"size":611644304,"categoryP":"video","categoryS":"hd___movies","magnet":"?xt=urn:btih:d47f9b798e451004b99a861eb0177dd28bce784d&amp;dn=Hop+%282011%29+-+Blu+ray+-+720p+-+Dual+Audio+%28Hindi-English%29+-+Team+&amp;tr=udp%3A%2F%2Ftracker.openbittorrent.com%3A80&amp;tr=udp%3A%2F%2Fopen.demonii.com%3A1337&amp;tr=udp%3A%2F%2Ftracker.coppersurfer.tk%3A6969&amp;tr=udp%3A%2F%2Fexodus.desync.com%3A6969","seeders":0,"leechers":0,"uploader":"saich9424","files":1,"time":1317225521,"description":" &lt;a href=&quot;http://www.impawards.com/2011/posters/hop.jpg&quot; rel=&quot;nofollow&quot; target=&quot;_NEW&quot;&gt;http://www.impawards.com/2011/posters/hop.jpg&lt;/a&gt; &lt;a href=&quot;\nhttp://img.sceper.eu/images/38rmo.jpg&quot; rel=&quot;nofollow&quot; target=&quot;_NEW&quot;&gt;\nhttp://img.sceper.eu/images/38rmo.jpg&lt;/a&gt; &lt;a href=&quot;\nhttp://img.sceper.eu/images/4ufqw.jpg&quot; rel=&quot;nofollow&quot; target=&quot;_NEW&quot;&gt;\nhttp://img.sceper.eu/images/4ufqw.jpg&lt;/a&gt; &lt;a href=&quot;\nhttp://img.sceper.eu/images/jnbdv.jpg&quot; rel=&quot;nofollow&quot; target=&quot;_NEW&quot;&gt;\nhttp://img.sceper.eu/images/jnbdv.jpg&lt;/a&gt; &lt;a href=&quot;\nhttp://img.sceper.eu/images/fw29j.jpg&quot; rel=&quot;nofollow&quot; target=&quot;_NEW&quot;&gt;\nhttp://img.sceper.eu/images/fw29j.jpg&lt;/a&gt; &lt;a href=&quot;\nhttp://img.sceper.eu/images/raqhk.jpg&quot; rel=&quot;nofollow&quot; target=&quot;_NEW&quot;&gt;\nhttp://img.sceper.eu/images/raqhk.jpg&lt;/a&gt; &lt;a href=&quot;\nhttp://img.sceper.eu/images/j5ysl.jpg&quot; rel=&quot;nofollow&quot; target=&quot;_NEW&quot;&gt;\nhttp://img.sceper.eu/images/j5ysl.jpg&lt;/a&gt; &lt;a href=&quot;\nhttp://img.sceper.eu/images/c1541.jpg&quot; rel=&quot;nofollow&quot; target=&quot;_NEW&quot;&gt;\nhttp://img.sceper.eu/images/c1541.jpg&lt;/a&gt; &lt;a href=&quot;\nhttp://img.sceper.eu/images/720p8.jpg&quot; rel=&quot;nofollow&quot; target=&quot;_NEW&quot;&gt;\nhttp://img.sceper.eu/images/720p8.jpg&lt;/a&gt;\n","torrent":{"xt":"urn:btih:d47f9b798e451004b99a861eb0177dd28bce784d","amp;dn":"Hop+%282011%29+-+Blu+ray+-+720p+-+Dual+Audio+%28Hindi-English%29+-+Team+","amp;tr":["udp%3A%2F%2Ftracker.openbittorrent.com%3A80","udp%3A%2F%2Fopen.demonii.com%3A1337","udp%3A%2F%2Ftracker.coppersurfer.tk%3A6969","udp%3A%2F%2Fexodus.desync.com%3A6969"],"infoHash":"d47f9b798e451004b99a861eb0177dd28bce784d","infoHashBuffer":{"type":"Buffer","data":[212,127,155,121,142,69,16,4,185,154,134,30,176,23,125,210,139,206,120,77]},"announce":[],"urlList":[]}}