{"title":"Ghost.Hunters.S07E16.Harvesting.Murder.HDTV.XviD-tNe.avi","uid":6708673,"size":366612480,"categoryP":"video","categoryS":"tv_shows","magnet":"?xt=urn:btih:dbbe4d1a6d92443d9ce5c009bdbebb5e50e95c2e&amp;dn=Ghost.Hunters.S07E16.Harvesting.Murder.HDTV.XviD-tNe.avi&amp;tr=udp%3A%2F%2Ftracker.openbittorrent.com%3A80&amp;tr=udp%3A%2F%2Fopen.demonii.com%3A1337&amp;tr=udp%3A%2F%2Ftracker.coppersurfer.tk%3A6969&amp;tr=udp%3A%2F%2Fexodus.desync.com%3A6969","seeders":0,"leechers":0,"uploader":"trialNerror","files":1,"time":1317273287,"description":"Ghost Hunters - Harvesting Murder\n \nAir Date: Sep 28, 2011\nRuntime: 43 minutes\nVideo: XviD @ 1000 Kpbs\nW x H: 624 x 352 (16:9)\nFrame: 29.97 fps\nAudio: Stereo MP3\nBitrate: Variable @ 128 Kbps\nSample rate: 48.0 KHz\nAlign: On Interleaves\n \nThe TAPS team travels to Hawaii's Plantation Village in Waipahu, Hawaii, in order to investigate claims of the paranormal and try to separate what could really be supernatural and what is natural.  Then the crew trades in their flip flops and tank tops for long johns and jackets to investigate the renovated Ventfort Hall in Lenox, Massachusetts, where people being touched, voices heard, and ghostly faces seen in a loft have been reported.","torrent":{"xt":"urn:btih:dbbe4d1a6d92443d9ce5c009bdbebb5e50e95c2e","amp;dn":"Ghost.Hunters.S07E16.Harvesting.Murder.HDTV.XviD-tNe.avi","amp;tr":["udp%3A%2F%2Ftracker.openbittorrent.com%3A80","udp%3A%2F%2Fopen.demonii.com%3A1337","udp%3A%2F%2Ftracker.coppersurfer.tk%3A6969","udp%3A%2F%2Fexodus.desync.com%3A6969"],"infoHash":"dbbe4d1a6d92443d9ce5c009bdbebb5e50e95c2e","infoHashBuffer":{"type":"Buffer","data":[219,190,77,26,109,146,68,61,156,229,192,9,189,190,187,94,80,233,92,46]},"announce":[],"urlList":[]}}