{"title":"Point Blank 2010 DVDRiP XviD-UNVEiL","uid":6726195,"size":740378720,"categoryP":"video","categoryS":"movies","magnet":"?xt=urn:btih:ea2190cf764724a48b3e3768d79d883042eb41b5&amp;dn=Point+Blank+2010+DVDRiP+XviD-UNVEiL&amp;tr=udp%3A%2F%2Ftracker.openbittorrent.com%3A80&amp;tr=udp%3A%2F%2Fopen.demonii.com%3A1337&amp;tr=udp%3A%2F%2Ftracker.coppersurfer.tk%3A6969&amp;tr=udp%3A%2F%2Fexodus.desync.com%3A6969","seeders":0,"leechers":0,"uploader":".BONE.","files":7,"time":1317960420,"description":" &lt;a href=&quot;http://www.piceye.net/pictures/b8955b900e71451ab32d1b07d08ca5d9.jpg&quot; rel=&quot;nofollow&quot; target=&quot;_NEW&quot;&gt;http://www.piceye.net/pictures/b8955b900e71451ab32d1b07d08ca5d9.jpg&lt;/a&gt;","torrent":{"xt":"urn:btih:ea2190cf764724a48b3e3768d79d883042eb41b5","amp;dn":"Point+Blank+2010+DVDRiP+XviD-UNVEiL","amp;tr":["udp%3A%2F%2Ftracker.openbittorrent.com%3A80","udp%3A%2F%2Fopen.demonii.com%3A1337","udp%3A%2F%2Ftracker.coppersurfer.tk%3A6969","udp%3A%2F%2Fexodus.desync.com%3A6969"],"infoHash":"ea2190cf764724a48b3e3768d79d883042eb41b5","infoHashBuffer":{"type":"Buffer","data":[234,33,144,207,118,71,36,164,139,62,55,104,215,157,136,48,66,235,65,181]},"announce":[],"urlList":[]}}