{"title":"Amy Ried - Fuck my ass","uid":6726585,"size":544514286,"categoryP":"porn","categoryS":"movie_clips","magnet":"?xt=urn:btih:f2c3a444523d831df08e7d6966d62fc3f3507bfb&amp;dn=Amy+Ried+-+Fuck+my+ass&amp;tr=udp%3A%2F%2Ftracker.openbittorrent.com%3A80&amp;tr=udp%3A%2F%2Fopen.demonii.com%3A1337&amp;tr=udp%3A%2F%2Ftracker.coppersurfer.tk%3A6969&amp;tr=udp%3A%2F%2Fexodus.desync.com%3A6969","seeders":0,"leechers":0,"uploader":null,"files":-1,"time":1317980760,"description":"Amy Ried - Fuck my ass\n  &lt;a href=&quot;\nhttp://sharezones.biz/view.php?filename=2011-10/07/ps9y1valth6p.jpg&quot; rel=&quot;nofollow&quot; target=&quot;_NEW&quot;&gt;\nhttp://sharezones.biz/view.php?filename=2011-10/07/ps9y1valth6p.jpg&lt;/a&gt;\n\nDirector: Vince Vouyer\nStarring: Amy Ried\n\nOne of the first anal scenes famous porn star Amy Ried. A scene cut from movie Keep 'Em Cummin' 2\n\nReleased: 2008\nIssued: Vouyer Media\nLength: 00:33:32\nLanguage: English\nGenre: Anal, Gonzo, Hardcore, Oral, Big Tits, Superstar\n\nQuality: DVDRip\nVideo: XviD, 704x416, 1972 kb / s\nSound: AC3, 2ch, 256 kb / s","torrent":{"xt":"urn:btih:f2c3a444523d831df08e7d6966d62fc3f3507bfb","amp;dn":"Amy+Ried+-+Fuck+my+ass","amp;tr":["udp%3A%2F%2Ftracker.openbittorrent.com%3A80","udp%3A%2F%2Fopen.demonii.com%3A1337","udp%3A%2F%2Ftracker.coppersurfer.tk%3A6969","udp%3A%2F%2Fexodus.desync.com%3A6969"],"infoHash":"f2c3a444523d831df08e7d6966d62fc3f3507bfb","infoHashBuffer":{"type":"Buffer","data":[242,195,164,68,82,61,131,29,240,142,125,105,102,214,47,195,243,80,123,251]},"announce":[],"urlList":[]}}