{"title":"Autentickavidea (STODOLNi 4) (Czech Amateur XXX)","uid":6723674,"size":253466581,"categoryP":"porn","categoryS":"movie_clips","magnet":"?xt=urn:btih:fc55b514b22971c721cd707f34d927d1e7eca6b4&amp;dn=Autentickavidea+%28STODOLNi+4%29+%28Czech+Amateur+XXX%29&amp;tr=udp%3A%2F%2Ftracker.openbittorrent.com%3A80&amp;tr=udp%3A%2F%2Fopen.demonii.com%3A1337&amp;tr=udp%3A%2F%2Ftracker.coppersurfer.tk%3A6969&amp;tr=udp%3A%2F%2Fexodus.desync.com%3A6969","seeders":0,"leechers":0,"uploader":"chkm8te","files":1,"time":1317879570,"description":"Screens: &lt;a href=&quot;\nhttp://4ufrom.me/viewer.php?file=6rnzyvf1ljrcwsav93kh.jpg&quot; rel=&quot;nofollow&quot; target=&quot;_NEW&quot;&gt;\nhttp://4ufrom.me/viewer.php?file=6rnzyvf1ljrcwsav93kh.jpg&lt;/a&gt;","torrent":{"xt":"urn:btih:fc55b514b22971c721cd707f34d927d1e7eca6b4","amp;dn":"Autentickavidea+%28STODOLNi+4%29+%28Czech+Amateur+XXX%29","amp;tr":["udp%3A%2F%2Ftracker.openbittorrent.com%3A80","udp%3A%2F%2Fopen.demonii.com%3A1337","udp%3A%2F%2Ftracker.coppersurfer.tk%3A6969","udp%3A%2F%2Fexodus.desync.com%3A6969"],"infoHash":"fc55b514b22971c721cd707f34d927d1e7eca6b4","infoHashBuffer":{"type":"Buffer","data":[252,85,181,20,178,41,113,199,33,205,112,127,52,217,39,209,231,236,166,180]},"announce":[],"urlList":[]}}